{"Q62096874":{"gemma3":{"en":{"all":["altar","candles","carpet","casket","ceiling","chair","church","cross","darkness","dog","figures","flowers","light","men","mourners","priest","room","scroll","shadows","table","walls","woman"],"animals":["dog"],"environment":["shadows","church","ceiling","room","walls"],"nature":["light","darkness"],"objects":["chair","casket","cross","table","candles","scroll","carpet","altar"],"people":["priest","figures","woman","men","mourners"],"plants":["flowers"],"unstructured":["A solemn scene depicts mourners gathered around a casket in a church room, illuminated by candlelight, with a priest and a dog present."]},"pt":{"all":["altar","velas","tapete","caixilharia","teto","cadeira","igreja","cruz","escuridão","cão","números","flores","luz","homens","enlutados","sacerdote","quarto","scroll","sombras","mesa","paredes","mulher"],"animals":["cão"],"environment":["sombras","igreja","teto","quarto","paredes"],"nature":["luz","escuridão"],"objects":["cadeira","caixilharia","cruz","mesa","velas","scroll","tapete","altar"],"people":["sacerdote","números","mulher","homens","enlutados"],"plants":["flores"],"unstructured":["uma cena solene retrata os enlutados reunidos ao redor de um caixão em uma sala de igreja, iluminados à luz de velas, com um padre e um cão presentes."]}}}}