{"Q62096560":{"gemma3":{"en":{"all":["darkness","figure","flower","frame","hand","light","oval","paper","portrait","scroll","shadow","woman"],"environment":["oval","frame","darkness"],"nature":["shadow","light"],"objects":["paper","hand","scroll"],"people":["figure","woman","portrait"],"plants":["flower"],"unstructured":["A melancholic woman holds a delicate paper scroll within a dark, ornate frame, illuminated by a soft, natural light."]},"pt":{"all":["escuridão","figura","flor","frame","mão","luz","oval","papel","retrato","scroll","sombra","mulher"],"environment":["oval","frame","escuridão"],"nature":["sombra","luz"],"objects":["papel","mão","scroll"],"people":["figura","mulher","retrato"],"plants":["flor"],"unstructured":["uma mulher melancólica segura um delicado rolo de papel dentro de um quadro escuro e ornamentado, iluminado por uma luz suave e natural."]}}}}