{"Q42713942":{"gemma3":{"en":{"all":["birds","buildings","cattle","clouds","foliage","grass","horizon","horses","houses","landscape","men","mountains","palms","ponies","riders","river","road","sky","trees","valley","vegetation","water"],"animals":["cattle","ponies"],"environment":["valley","mountains","horizon","landscape"],"fauna":["birds"],"flora":["palms"],"nature":["clouds","water","sky","grass"],"objects":["houses","road","river"],"people":["riders","horses","men","buildings"],"plants":["vegetation","trees","foliage"],"unstructured":["A picturesque valley scene depicts rural houses, horses, and lush vegetation alongside a river, framed by distant mountains and a bright sky."]},"pt":{"all":["aves","edifícios","bovinos","nuvens","folhagem","gramíneas","horizonte","cavalos","casas","paisagem","homens","montanhas","palmas","pôneis","cavaleiros","rio","estrada","céu","árvores","vale","vegetação","água"],"animals":["bovinos","pôneis"],"environment":["vale","montanhas","horizonte","paisagem"],"fauna":["aves"],"flora":["palmas"],"nature":["nuvens","água","céu","gramíneas"],"objects":["casas","estrada","rio"],"people":["cavaleiros","cavalos","homens","edifícios"],"plants":["vegetação","árvores","folhagem"],"unstructured":["uma cena pitoresca do vale retrata casas rurais, cavalos e vegetação exuberante ao lado de um rio, emoldurado por montanhas distantes e um céu brilhante."]}}}}