{"Q52301957":{"gemma3":{"en":{"all":["animals","birds","branches","building","carriage","clouds","columns","door","foliage","horses","men","people","roof","shadows","sky","square","street","sun","trees","wall","windows"],"animals":["carriage","horses","animals"],"environment":["square","roof","building","wall","street"],"fauna":["birds"],"flora":["trees","foliage"],"nature":["clouds","sky","sun"],"objects":["door","columns","shadows","carriage","windows"],"people":["horses","shadows","people","men","carriage"],"plants":["branches"],"unstructured":["A painted scene depicts a bustling street with a grand building, horses in carriages, and people enjoying a sunny day."]},"pt":{"all":["animais","aves","ramos","edifício","transporte","nuvens","colunas","porta","folhagem","cavalos","homens","pessoas","telhado","sombras","céu","quadrado","rua","sol","árvores","parede","windows"],"animals":["transporte","cavalos","animais"],"environment":["quadrado","telhado","edifício","parede","rua"],"fauna":["aves"],"flora":["árvores","folhagem"],"nature":["nuvens","céu","sol"],"objects":["porta","colunas","sombras","transporte","windows"],"people":["cavalos","sombras","pessoas","homens","transporte"],"plants":["ramos"],"unstructured":["uma cena pintada retrata uma rua movimentada com um grande edifício, cavalos em carruagens e pessoas desfrutando de um dia ensolarado."]}}}}