{"Q52303614":{"gemma3":{"en":{"all":["background","birds","branches","creatures","figures","flowers","foliage","ink","leaves","lines","paper","pen","roots","scroll","vines","women"],"animals":["creatures"],"environment":["paper","background","scroll"],"fauna":["birds"],"flora":["flowers","foliage"],"nature":["branches","roots","leaves"],"objects":["pen","lines","ink"],"people":["women","figures","creatures"],"plants":["vines"],"unstructured":["A detailed, antique drawing depicts fantastical women entwined with foliage and birds amidst a scroll-like background."]},"pt":{"all":["fundo","aves","ramos","criaturas","números","flores","folhagem","tinta","folhas","linhas","papel","caneta","raízes","scroll","vinhas","mulheres"],"animals":["criaturas"],"environment":["papel","fundo","scroll"],"fauna":["aves"],"flora":["flores","folhagem"],"nature":["ramos","raízes","folhas"],"objects":["caneta","linhas","tinta"],"people":["mulheres","números","criaturas"],"plants":["vinhas"],"unstructured":["um desenho detalhado e antigo retrata mulheres fantásticas entrelaçadas com folhagem e pássaros em meio a um fundo semelhante a um pergaminho."]}}}}