{"Q52303067":{"gemma3":{"en":{"all":["background","blossoms","canvas","collar","face","figure","flora","flowers","jacket","leaves","man","painting","petals","portrait","tie"],"environment":["canvas","background","painting"],"flora":["flowers","blossoms"],"nature":["leaves","flora"],"objects":["collar","tie","jacket"],"people":["figure","man","portrait","face"],"plants":["petals"],"unstructured":["A weathered man wears a dark jacket adorned with yellow blossoms, creating a poignant portrait against a warm, earthy background."]},"pt":{"all":["fundo","flores","canvas","gola","face","figura","flora","flores","jaqueta","folhas","homem","pintura","pétalas","retrato","gravata"],"environment":["canvas","fundo","pintura"],"flora":["flores","flores"],"nature":["folhas","flora"],"objects":["gola","gravata","jaqueta"],"people":["figura","homem","retrato","face"],"plants":["pétalas"],"unstructured":["um homem desgastado usa uma jaqueta escura adornada com flores amarelas, criando um retrato pungente contra um fundo quente e terroso."]}}}}