{"Q59925147":{"gemma3":{"en":{"all":["Background","Canvas","Darkness","Figure","Light","Man","Portrait","Rectangle","Shadows","Signature","Subject","Texture"],"environment":["Background","Canvas","Darkness"],"nature":["Texture","Shadows","Light"],"objects":["Signature","Rectangle"],"people":["Man","Figure","Subject","Portrait"],"unstructured":["A portrait of an elderly man in a dark background, illuminated by subtle light, with a rectangular signature and a formal black attire."]},"pt":{"all":["antecedentes","canvas","escuridão","figura","luz","homem","retrato","retângulo","sombras","assinatura","assunto","textura"],"environment":["antecedentes","canvas","escuridão"],"nature":["textura","sombras","luz"],"objects":["assinatura","retângulo"],"people":["homem","figura","assunto","retrato"],"unstructured":["um retrato de um homem idoso em um fundo escuro, iluminado por luz sutil, com uma assinatura retangular e um traje preto formal."]}}}}