{"Q62033531":{"gemma3":{"en":{"all":["arm","background","bird","clothing","figure","grass","hand","horse","landscape","light","man","paper","shadow","sketch","sky","soldier","space","sword","tree"],"animals":["horse"],"environment":["space","background","landscape"],"fauna":["bird"],"flora":["tree"],"nature":["shadow","light","sky"],"objects":["sword","paper","sketch","clothing"],"people":["soldier","man","figure","arm","hand"],"plants":["grass"],"unstructured":["A sketched soldier stands in a landscape, holding a sword, with a horse and tree in the background."]},"pt":{"all":["braço","fundo","ave","roupas","figura","gramíneas","mão","cavalo","paisagem","luz","homem","papel","sombra","sketch","céu","soldado","espaço","espada","árvore"],"animals":["cavalo"],"environment":["espaço","fundo","paisagem"],"fauna":["ave"],"flora":["árvore"],"nature":["sombra","luz","céu"],"objects":["espada","papel","sketch","roupas"],"people":["soldado","homem","figura","braço","mão"],"plants":["gramíneas"],"unstructured":["um soldado esboçado está em uma paisagem, segurando uma espada, com um cavalo e uma árvore no fundo."]}}}}