{"Q43267478":{"gemma3":{"en":{"all":["artist","background","bird","candle","earth","figure","flowers","foliage","fruit","garden","glass","ivy","lamp","landscape","leaves","lilies","man","peacock","room","roses","shadows","space","table","tray","vase","vines"],"animals":["bird"],"environment":["room","background","space"],"fauna":["peacock"],"flora":["roses","flowers","lilies"],"nature":["earth","garden","landscape"],"objects":["shadows","lamp","fruit","table","candle","tray","glass","vase"],"people":["man","artist","figure"],"plants":["leaves","vines","ivy","foliage"],"unstructured":["A painter depicts a luxurious still life with a red pillar, fruit, flowers, and shadows within a dimly lit room."]},"pt":{"all":["artista","fundo","ave","vela","terra","figura","flores","folhagem","frutos","jardim","vidro","hera","lâmpada","paisagem","folhas","lírios","homem","pavão","quarto","rosas","sombras","espaço","mesa","bandeja","vaso","vinhas"],"animals":["ave"],"environment":["quarto","fundo","espaço"],"fauna":["pavão"],"flora":["rosas","flores","lírios"],"nature":["terra","jardim","paisagem"],"objects":["sombras","lâmpada","frutos","mesa","vela","bandeja","vidro","vaso"],"people":["homem","artista","figura"],"plants":["folhas","vinhas","hera","folhagem"],"unstructured":["um pintor retrata uma luxuosa natureza morta com um pilar vermelho, frutas, flores e sombras dentro de uma sala mal iluminada."]}}}}