{"Q50993843":{"gemma3":{"en":{"all":["bird","box","chain","darkness","face","figure","flowers","gold","hand","ivy","jewel","light","man","raven","room","scroll","shadows","stone","surface","texture","wall","woman"],"animals":["bird"],"environment":["shadows","wall","stone","darkness","room"],"fauna":["raven"],"flora":["ivy"],"nature":["surface","light","gold","texture"],"objects":["jewel","chain","scroll","box"],"people":["woman","face","man","hand","figure"],"plants":["flowers"],"unstructured":["A dark-skinned man holds a jeweled box near a woman, surrounded by shadows and a raven in a stone room."]},"pt":{"all":["ave","caixa","cadeia","escuridão","face","figura","flores","ouro","mão","hera","joia","luz","homem","corvo","quarto","scroll","sombras","pedra","superfície","textura","parede","mulher"],"animals":["ave"],"environment":["sombras","parede","pedra","escuridão","quarto"],"fauna":["corvo"],"flora":["hera"],"nature":["superfície","luz","ouro","textura"],"objects":["joia","cadeia","scroll","caixa"],"people":["mulher","face","homem","mão","figura"],"plants":["flores"],"unstructured":["um homem de pele escura segura uma caixa de jóias perto de uma mulher, cercada por sombras e um corvo em uma sala de pedra."]}}}}