{"Q59826086":{"objects":[{"box":[0.7361,0.3222,0.9975,0.7563],"label":"vegetation","score":0.184},{"box":[0.2672,0.5481,0.5407,0.7117],"label":"vegetation","score":0.242},{"box":[0.0059,0.4988,0.2867,0.6752],"label":"vegetation","score":0.165},{"box":[0.5303,0.5659,0.6368,0.7223],"label":"tree","score":0.185},{"box":[0.9404,0.5675,1.0013,0.8166],"label":"tree","score":0.331},{"box":[0.6121,0.5921,0.7764,0.7394],"label":"tree","score":0.15},{"box":[0.7693,0.6914,0.9146,0.8224],"label":"tree","score":0.202},{"box":[0.5621,0.7426,0.8777,1.0002],"label":"vegetation","score":0.337},{"box":[0.5303,0.5902,0.5853,0.7251],"label":"palm tree","score":0.325},{"box":[0.9404,0.5675,1.0013,0.8166],"label":"palm tree","score":0.316},{"box":[0.6414,0.5948,0.7216,0.7334],"label":"conifer","score":0.216},{"box":[0.7693,0.6914,0.9146,0.8224],"label":"palm tree","score":0.274}]}}