{"F14087":{"gemma3":{"en":{"all":["animal","background","creature","earth","figures","forms","ground","humanoids","models","plants","shapes","space","statues","surface","vegetation","void","wildlife"],"animals":["animal","creature"],"environment":["space","background","void"],"fauna":["wildlife"],"flora":["plants"],"nature":["surface","earth","ground"],"objects":["forms","shapes"],"people":["figures","models","statues","humanoids"],"plants":["vegetation"],"unstructured":["Several humanoid figures stand precariously balanced on a dark, undefined surface, creating a surreal and unsettling scene."]},"pt":{"all":["animal","fundo","criatura","terra","números","formulários","terra","humanóides","modelos","plantas","formas","espaço","estátuas","superfície","vegetação","vazio","vida selvagem"],"animals":["animal","criatura"],"environment":["espaço","fundo","vazio"],"fauna":["vida selvagem"],"flora":["plantas"],"nature":["superfície","terra","terra"],"objects":["formulários","formas"],"people":["números","modelos","estátuas","humanóides"],"plants":["vegetação"],"unstructured":["várias figuras humanóides estão precariamente equilibradas em uma superfície escura e indefinida, criando uma cena surreal e inquietante."]}}}}