{"F143872":{"gemma3":{"en":{"all":["Brand","Cans","Color","Glasses","Light","Liquid","Logo","Man","Metal","Oil","Pattern","Room","Shelves","Shirt","Spot","Surface","Table","Text"],"environment":["Surface","Room","Table","Light"],"nature":["Spot","Liquid","Oil"],"objects":["Brand","Text","Cans","Metal","Color","Logo","Shelves"],"people":["Pattern","Glasses","Man","Shirt"],"unstructured":["A man observes a collection of vintage oil cans arranged on a table, illuminated by a bright light reflecting onto a dark surface."]},"pt":{"all":["marca","latas","cor","culos","luz","líquido","logo","homem","metal","leo","padrão","quarto","prateleiras","camisa","spot","superfície","quadro","texto"],"environment":["superfície","quarto","quadro","luz"],"nature":["spot","líquido","leo"],"objects":["marca","texto","latas","metal","cor","logo","prateleiras"],"people":["padrão","culos","homem","camisa"],"unstructured":["um homem observa uma coleção de latas de óleo vintage dispostas em uma mesa, iluminadas por uma luz brilhante refletindo em uma superfície escura."]}}}}