{"F191903":{"gemma3":{"en":{"all":["beach","bird","bush","coastline","figure","grass","greenery","horizon","landscape","moss","path","person","road","rocks","sand","sea","seagull","sky","stone","vegetation","walker","water","waves","wildlife"],"animals":["seagull","bird"],"environment":["coastline","horizon","sea","beach","landscape"],"fauna":["wildlife"],"flora":["greenery"],"nature":["sky","rocks","sand","water","waves"],"objects":["path","stone","road"],"people":["figure","person","walker"],"plants":["bush","vegetation","moss","grass"],"unstructured":["A solitary walker traverses a coastal path alongside a serene beach, reflecting the vastness of the sea and the natural beauty of the landscape."]},"pt":{"all":["praia","ave","mato","litoral","figura","gramíneas","esverdeamento","horizonte","paisagem","musgo","caminho","pessoa","estrada","rochas","areia","mar","gaivota","céu","pedra","vegetação","walker","água","ondas","vida selvagem"],"animals":["gaivota","ave"],"environment":["litoral","horizonte","mar","praia","paisagem"],"fauna":["vida selvagem"],"flora":["esverdeamento"],"nature":["céu","rochas","areia","água","ondas"],"objects":["caminho","pedra","estrada"],"people":["figura","pessoa","walker"],"plants":["mato","vegetação","musgo","gramíneas"],"unstructured":["um caminhante solitário percorre um caminho costeiro ao longo de uma praia serena, refletindo a vastidão do mar e a beleza natural da paisagem."]}}}}