{"F194999":{"gemma3":{"en":{"all":["advertising","birds","building","city","drivers","light","lights","motorcycles","night","panels","pedestrians","people","reflection","shadows","signs","sky","street","structure","trees","urban","vehicles"],"environment":["sky","street","night","city","building","urban"],"fauna":["birds"],"flora":["trees"],"nature":["light","reflection","shadows"],"objects":["structure","advertising","signs","panels","lights"],"people":["motorcycles","drivers","vehicles","pedestrians","people"],"unstructured":["A brightly illuminated triangular structure dominates a nighttime cityscape, reflecting colorful lights and casting shadows on the surrounding buildings and busy street."]},"pt":{"all":["publicidade","aves","edifício","cidade","motoristas","luz","luzes","motocicletas","noite","painéis","peões","pessoas","reflexão","sombras","sinais","céu","rua","estrutura","árvores","urbano","veículos"],"environment":["céu","rua","noite","cidade","edifício","urbano"],"fauna":["aves"],"flora":["árvores"],"nature":["luz","reflexão","sombras"],"objects":["estrutura","publicidade","sinais","painéis","luzes"],"people":["motocicletas","motoristas","veículos","peões","pessoas"],"unstructured":["uma estrutura triangular brilhantemente iluminada domina uma paisagem noturna, refletindo luzes coloridas e lançando sombras nos edifícios circundantes e na rua movimentada."]}}}}