{"F307387":{"gemma3":{"en":{"all":["blue","box","boy","color","headphones","image","listener","room","screen","space","surface","wall"],"environment":["space","wall","room","surface"],"nature":["color","blue"],"objects":["headphones","image","box","screen"],"people":["boy","listener"],"unstructured":["A boy listens intently to an image on a screen within a colorful room, surrounded by geometric shapes and a vibrant blue wall."]},"pt":{"all":["azul","caixa","menino","cor","fones de ouvido","imagem","ouvinte","quarto","tela","espaço","superfície","parede"],"environment":["espaço","parede","quarto","superfície"],"nature":["cor","azul"],"objects":["fones de ouvido","imagem","caixa","tela"],"people":["menino","ouvinte"],"unstructured":["um menino ouve atentamente uma imagem em uma tela dentro de uma sala colorida, cercada por formas geométricas e uma parede azul vibrante."]}}}}