{"F407775":{"gemma3":{"en":{"all":["animals","background","beasts","birds","creatures","earth","faces","figures","flowers","foliage","forms","humans","individuals","landscape","leaves","moss","patterns","pixels","plants","shapes","sky","space","species","terrain","texture","vegetation","void","wildlife"],"animals":["beasts","creatures"],"environment":["sky","background","void","space"],"fauna":["birds","species","wildlife","animals"],"flora":["plants","vegetation","flowers","leaves"],"nature":["earth","texture","landscape","terrain"],"objects":["forms","patterns","pixels","shapes"],"people":["faces","figures","individuals","humans"],"plants":["moss","foliage"],"unstructured":["The image presents a chaotic, densely layered composition of fragmented human and natural forms, creating a disorienting and abstract visual experience."]},"pt":{"all":["animais","fundo","bestas","aves","criaturas","terra","faces","números","flores","folhagem","formulários","humanos","indivíduos","paisagem","folhas","musgo","padrões","pixels","plantas","formas","céu","espaço","espécie","terreno","textura","vegetação","vazio","vida selvagem"],"animals":["bestas","criaturas"],"environment":["céu","fundo","vazio","espaço"],"fauna":["aves","espécie","vida selvagem","animais"],"flora":["plantas","vegetação","flores","folhas"],"nature":["terra","textura","paisagem","terreno"],"objects":["formulários","padrões","pixels","formas"],"people":["faces","números","indivíduos","humanos"],"plants":["musgo","folhagem"],"unstructured":["a imagem apresenta uma composição caótica e densamente em camadas de formas humanas e naturais fragmentadas, criando uma experiência visual desorientadora e abstrata."]}}}}