{"F416287":{"gemma3":{"en":{"all":["background","bird","feather","flora","form","grass","grasses","human","insect","line","observer","plant","space","stem","surface","texture"],"animals":["bird"],"environment":["space","background","texture","surface"],"fauna":["insect"],"flora":["grasses","feather"],"nature":["stem","plant","grass"],"objects":["line","form"],"people":["human","observer"],"plants":["flora","stem"],"unstructured":["A solitary feather rests delicately on a dark, textured background, evoking a sense of quiet contemplation and natural beauty."]},"pt":{"all":["fundo","ave","penas","flora","formulário","gramíneas","gramíneas","humano","inseto","linha","observador","planta","espaço","caule","superfície","textura"],"animals":["ave"],"environment":["espaço","fundo","textura","superfície"],"fauna":["inseto"],"flora":["gramíneas","penas"],"nature":["caule","planta","gramíneas"],"objects":["linha","formulário"],"people":["humano","observador"],"plants":["flora","caule"],"unstructured":["uma pena solitária repousa delicadamente sobre um fundo escuro e texturizado, evocando uma sensação de contemplação silenciosa e beleza natural."]}}}}