{"F66724":{"gemma3":{"en":{"all":["background","bird","branch","curve","figure","flower","forest","human","insect","leaf","line","pattern","roots","shape","space","stem","stripes","surface","texture","tree"],"animals":["bird"],"environment":["surface","texture","space","background","pattern"],"fauna":["insect"],"flora":["leaf"],"nature":["tree","roots","branch","forest"],"objects":["line","curve","shape","stripes"],"people":["figure","human"],"plants":["stem","flower"],"unstructured":["A stylized, abstract background features repeating blue lines against a warm yellow surface, evoking a sense of depth and natural patterns."]},"pt":{"all":["fundo","ave","ramo","curva","figura","flor","floresta","humano","inseto","folha","linha","padrão","raízes","forma","espaço","caule","listras","superfície","textura","árvore"],"animals":["ave"],"environment":["superfície","textura","espaço","fundo","padrão"],"fauna":["inseto"],"flora":["folha"],"nature":["árvore","raízes","ramo","floresta"],"objects":["linha","curva","forma","listras"],"people":["figura","humano"],"plants":["caule","flor"],"unstructured":["um fundo estilizado e abstrato apresenta linhas azuis repetidas contra uma superfície amarela quente, evocando uma sensação de profundidade e padrões naturais."]}}}}