{"F82969":{"gemma3":{"en":{"all":["area","background","devices","hands","individuals","light","person","screens","shadow","space","squares","tone"],"environment":["space","area","background"],"nature":["light","tone","shadow"],"objects":["squares","screens","devices"],"people":["hands","person","individuals"],"unstructured":["Several people are interacting with illuminated square screens in a dimly lit environment, creating a modern and focused scene."]},"pt":{"all":["área","fundo","dispositivos","mãos","indivíduos","luz","pessoa","telas","sombra","espaço","quadrados","tom"],"environment":["espaço","área","fundo"],"nature":["luz","tom","sombra"],"objects":["quadrados","telas","dispositivos"],"people":["mãos","pessoa","indivíduos"],"unstructured":["várias pessoas estão interagindo com telas quadradas iluminadas em um ambiente mal iluminado, criando uma cena moderna e focada."]}}}}