{"Q49871308":{"gemma3":{"en":{"all":["background","bird","books","carpet","chair","chamber","darkness","feather","figure","flower","globe","gown","hat","light","man","medal","necklace","portrait","room","shadow","space","statue","subject","table","wall"],"animals":["bird"],"environment":["chamber","space","background","room","wall"],"fauna":["feather"],"flora":["carpet"],"nature":["shadow","light","darkness"],"objects":["statue","chair","medal","necklace","hat","table","globe","books","gown"],"people":["subject","figure","man","portrait"],"plants":["flower"],"unstructured":["A distinguished man in a dark gown stands in a richly decorated room, holding a hat and medals before a classical statue."]},"pt":{"all":["fundo","ave","livros","tapete","cadeira","câmara","escuridão","penas","figura","flor","globo","vestido","chapéu","luz","homem","medalha","colar","retrato","quarto","sombra","espaço","estátua","assunto","mesa","parede"],"animals":["ave"],"environment":["câmara","espaço","fundo","quarto","parede"],"fauna":["penas"],"flora":["tapete"],"nature":["sombra","luz","escuridão"],"objects":["estátua","cadeira","medalha","colar","chapéu","mesa","globo","livros","vestido"],"people":["assunto","figura","homem","retrato"],"plants":["flor"],"unstructured":["um homem distinto em um vestido escuro está em uma sala ricamente decorada, segurando um chapéu e medalhas diante de uma estátua clássica."]}}}}