{"Q49877820":{"gemma3":{"en":{"all":["background","bird","face","figure","flower","gown","hands","jewel","leaf","man","mask","necklace","petals","portrait","raven","red","ring","room","rose","wall"],"animals":["bird"],"environment":["wall","room","background"],"fauna":["raven"],"flora":["petals"],"nature":["leaf","red","flower"],"objects":["jewel","necklace","mask","gown","ring"],"people":["hands","man","figure","face","portrait"],"plants":["rose"],"unstructured":["A man in a dark gown with a red rose and jewel adornments sits in a room with a background wall."]},"pt":{"all":["fundo","ave","face","figura","flor","vestido","mãos","joia","folha","homem","máscara","colar","pétalas","retrato","corvo","vermelho","anel","quarto","rosa","parede"],"animals":["ave"],"environment":["parede","quarto","fundo"],"fauna":["corvo"],"flora":["pétalas"],"nature":["folha","vermelho","flor"],"objects":["joia","colar","máscara","vestido","anel"],"people":["mãos","homem","figura","face","retrato"],"plants":["rosa"],"unstructured":["um homem em um vestido escuro com uma rosa vermelha e adornos de jóias senta-se em uma sala com uma parede de fundo."]}}}}