{"Q49864267":{"gemma3":{"en":{"all":["birds","boats","buildings","clouds","dock","harbor","horses","men","officers","pedestrians","pillars","quay","reflection","sailors","seagulls","shore","sky","stone","trees","vegetation","water"],"animals":["horses","boats","seagulls"],"environment":["quay","water","dock","buildings","harbor","shore"],"fauna":["birds"],"flora":["trees"],"nature":["clouds","reflection","sky"],"objects":["water","boats","stone","buildings","pillars"],"people":["officers","pedestrians","horses","sailors","men"],"plants":["vegetation"],"unstructured":["Sailors navigate a tranquil harbor, reflecting in the water, surrounded by buildings and nature's serene beauty."]},"pt":{"all":["aves","barcos","edifícios","nuvens","doca","porto","cavalos","homens","oficiais","peões","pilares","quay","reflexão","marinheiros","gaivotas","costa","céu","pedra","árvores","vegetação","água"],"animals":["cavalos","barcos","gaivotas"],"environment":["quay","água","doca","edifícios","porto","costa"],"fauna":["aves"],"flora":["árvores"],"nature":["nuvens","reflexão","céu"],"objects":["água","barcos","pedra","edifícios","pilares"],"people":["oficiais","peões","cavalos","marinheiros","homens"],"plants":["vegetação"],"unstructured":["os marinheiros navegam por um porto tranquilo, refletindo na água, cercado por edifícios e pela beleza serena da natureza."]}}}}