{"Q105678884":{"objects":[{"box":[0.1206,0.8141,0.2319,0.9125],"label":"ox","score":0.283},{"box":[0.7562,0.0108,0.979,0.5557],"label":"tree","score":0.156},{"box":[0.0237,0.0196,0.4953,0.842],"label":"tree","score":0.225},{"box":[0.4696,0.0132,0.5953,0.8726],"label":"tree","score":0.208},{"box":[0.4956,0.0142,0.9838,0.8846],"label":"tree","score":0.188},{"box":[0.4948,0.4264,0.6138,0.8779],"label":"tree","score":0.183},{"box":[0.7229,0.4999,0.9959,0.904],"label":"bush","score":0.206},{"box":[0.0192,0.4439,0.9851,0.9396],"label":"vegetation","score":0.303},{"box":[0.0162,0.8184,0.98,0.945],"label":"vegetation","score":0.339},{"box":[0.7562,0.0108,0.979,0.5557],"label":"palm tree","score":0.31},{"box":[0.0432,0.1668,0.2343,0.782],"label":"palm tree","score":0.357},{"box":[0.0237,0.0196,0.4953,0.842],"label":"palm tree","score":0.325},{"box":[0.3125,0.0923,0.4856,0.8584],"label":"palm tree","score":0.208},{"box":[0.4956,0.0142,0.9838,0.8846],"label":"palm tree","score":0.289},{"box":[0.682,0.2762,0.8376,0.8806],"label":"palm tree","score":0.297}]}}