{"Q102889974":{"gemma3":{"en":{"all":["bank","birds","bucket","clouds","duck","figure","flowers","foliage","grass","landscape","person","rag","river","scene","shore","sky","stone","swans","trees","vegetation","water","wheelbarrow","wildlife","willow","woman"],"animals":["birds","swans","duck"],"environment":["river","scene","landscape","bank","shore"],"fauna":["wildlife"],"flora":["flowers"],"nature":["sky","water","clouds","vegetation","grass"],"objects":["bucket","rag","water","stone","wheelbarrow"],"people":["figure","woman","person"],"plants":["trees","willow","foliage"],"unstructured":["A woman washes laundry by a riverbank, utilizing a wheelbarrow and bucket amidst lush greenery and waterfowl."]},"pt":{"all":["banco","aves","balde","nuvens","pato","figura","flores","folhagem","gramíneas","paisagem","pessoa","rag","rio","cena","costa","céu","pedra","cisnes","árvores","vegetação","água","wheelbarrow","vida selvagem","salgueiro","mulher"],"animals":["aves","cisnes","pato"],"environment":["rio","cena","paisagem","banco","costa"],"fauna":["vida selvagem"],"flora":["flores"],"nature":["céu","água","nuvens","vegetação","gramíneas"],"objects":["balde","rag","água","pedra","wheelbarrow"],"people":["figura","mulher","pessoa"],"plants":["árvores","salgueiro","folhagem"],"unstructured":["uma mulher lava a roupa em uma margem do rio, utilizando um carrinho de mão e balde em meio a vegetação exuberante e aves aquáticas."]}}}}