{"Q19860088":{"gemma3":{"en":{"all":["background","beak","canvas","coat","collar","eyes","face","figure","gray","hands","man","painting","portrait","shade","subject","tie","tone"],"animals":["beak"],"environment":["canvas","background","painting"],"nature":["gray","shade","tone"],"objects":["hands","face","collar","tie","coat","eyes"],"people":["subject","figure","man","portrait"],"unstructured":["A distinguished man in a black coat and white tie gazes solemnly from a gray canvas, embodying a timeless portrait."]},"pt":{"all":["fundo","bico","canvas","pelagem","gola","olhos","face","figura","cinza","mãos","homem","pintura","retrato","sombra","assunto","gravata","tom"],"animals":["bico"],"environment":["canvas","fundo","pintura"],"nature":["cinza","sombra","tom"],"objects":["mãos","face","gola","gravata","pelagem","olhos"],"people":["assunto","figura","homem","retrato"],"unstructured":["um homem distinto em um casaco preto e gravata branca olha solenemente de uma tela cinza, incorporando um retrato atemporal."]}}}}