{"Q59856926":{"gemma3":{"en":{"all":["face","figure","hair","head","paper","pencil","portrait","ribbon","scarf","shade","sketch","tone","woman"],"environment":["paper","sketch"],"nature":["shade","tone"],"objects":["hair","pencil","head","ribbon"],"people":["figure","portrait","woman","face"],"plants":["scarf"],"unstructured":["A woman's head and shoulders are depicted in a pencil sketch, with a scarf and a thoughtful expression."]},"pt":{"all":["face","figura","cabelo","cabeça","papel","lápis","retrato","fita","cachecol","sombra","sketch","tom","mulher"],"environment":["papel","sketch"],"nature":["sombra","tom"],"objects":["cabelo","lápis","cabeça","fita"],"people":["figura","retrato","mulher","face"],"plants":["cachecol"],"unstructured":["a cabeça e os ombros de uma mulher são retratados em um esboço de lápis, com um lenço e uma expressão pensativa."]}}}}