{"MU16372":{"gemma3":{"en":{"all":["area","atmosphere","background","bird","child","cloak","clouds","creature","face","figure","foliage","hat","leaves","owl","sky","space","woman"],"animals":["bird","owl"],"environment":["area","background","space"],"fauna":["creature"],"flora":["foliage"],"nature":["clouds","sky","atmosphere"],"objects":["cloak","hat"],"people":["figure","woman","child","face"],"plants":["leaves"],"unstructured":["A ghostly child and woman, shrouded in a dark cloak, are surrounded by ethereal clouds and a solitary owl in a misty environment."]},"pt":{"all":["área","atmosfera","fundo","ave","criança","camuflagem","nuvens","criatura","face","figura","folhagem","chapéu","folhas","coruja","céu","espaço","mulher"],"animals":["ave","coruja"],"environment":["área","fundo","espaço"],"fauna":["criatura"],"flora":["folhagem"],"nature":["nuvens","céu","atmosfera"],"objects":["camuflagem","chapéu"],"people":["figura","mulher","criança","face"],"plants":["folhas"],"unstructured":["uma criança e uma mulher fantasmagóricas, envoltas em um manto escuro, estão cercadas por nuvens etéreas e uma coruja solitária em um ambiente nebuloso."]}}}}