{"MU16912":{"gemma3":{"en":{"all":["background","bird","branch","face","figure","hair","hat","head","leaves","roots","rope","scarf","space","tree","wall","woman"],"environment":["wall","background","space"],"fauna":["bird"],"flora":["leaves"],"nature":["roots","tree","branch"],"objects":["hat","scarf","rope"],"people":["figure","woman","face","hair","head"],"unstructured":["A melancholic woman in a hat gazes into the distance, surrounded by a somber background of tree branches and a muted environment."]},"pt":{"all":["fundo","ave","ramo","face","figura","cabelo","chapéu","cabeça","folhas","raízes","corda","cachecol","espaço","árvore","parede","mulher"],"environment":["parede","fundo","espaço"],"fauna":["ave"],"flora":["folhas"],"nature":["raízes","árvore","ramo"],"objects":["chapéu","cachecol","corda"],"people":["figura","mulher","face","cabelo","cabeça"],"unstructured":["uma mulher melancólica em um chapéu olha para a distância, cercada por um fundo sombrio de galhos de árvores e um ambiente mudo."]}}}}