{"MU17935":{"gemma3":{"en":{"all":["arms","background","belt","bird","branch","bush","buttons","coat","collar","ears","eyes","face","figure","glasses","hands","head","leaves","man","mouth","nose","paper","sky","stem","tie","tree","wind"],"environment":["sky","tree","paper","background"],"fauna":["bird"],"flora":["leaves"],"nature":["wind","branch"],"objects":["belt","buttons","glasses","collar","tie","coat"],"people":["ears","hands","man","figure","mouth","face","arms","eyes","head","nose"],"plants":["bush","stem"],"unstructured":["A whimsical man with glasses and a coat is drawn in a simple style against a tree and a cloudy background."]},"pt":{"all":["braços","fundo","cinto","ave","ramo","mato","botões","pelagem","gola","orelhas","olhos","face","figura","óculos","mãos","cabeça","folhas","homem","boca","nariz","papel","céu","caule","gravata","árvore","vento"],"environment":["céu","árvore","papel","fundo"],"fauna":["ave"],"flora":["folhas"],"nature":["vento","ramo"],"objects":["cinto","botões","óculos","gola","gravata","pelagem"],"people":["orelhas","mãos","homem","figura","boca","face","braços","olhos","cabeça","nariz"],"plants":["mato","caule"],"unstructured":["um homem caprichoso com óculos e um casaco é desenhado em um estilo simples contra uma árvore e um fundo nublado."]}}}}