{"MU17642":{"gemma3":{"en":{"all":["bird","building","bush","column","deer","fence","figure","flower","garden","ground","landscape","lion","lotus","man","mountain","person","pillar","platform","sky","statue","stone","structure","tree","vine","wall"],"animals":["bird","lion"],"environment":["landscape","structure","building","wall","garden"],"fauna":["deer"],"flora":["lotus"],"nature":["sky","tree","stone","ground","mountain"],"objects":["fence","statue","column","platform","pillar"],"people":["figure","man","person"],"plants":["vine","bush","flower"],"unstructured":["A serene drawing depicts a man observing a stone statue of Buddha within a detailed garden setting, surrounded by lush flora and a distant mountain landscape."]},"pt":{"all":["ave","edifício","mato","coluna","veado","cerca","figura","flor","jardim","terra","paisagem","leão","lótus","homem","montanha","pessoa","pilar","plataforma","céu","estátua","pedra","estrutura","árvore","vinha","parede"],"animals":["ave","leão"],"environment":["paisagem","estrutura","edifício","parede","jardim"],"fauna":["veado"],"flora":["lótus"],"nature":["céu","árvore","pedra","terra","montanha"],"objects":["cerca","estátua","coluna","plataforma","pilar"],"people":["figura","homem","pessoa"],"plants":["vinha","mato","flor"],"unstructured":["um desenho sereno retrata um homem observando uma estátua de pedra de buda dentro de um cenário de jardim detalhado, cercado por uma flora exuberante e uma paisagem montanhosa distante."]}}}}