{"MU17238":{"gemma3":{"en":{"all":["artist","background","bird","fabric","figure","flower","fruit","leaves","plate","shadow","space","stem","surface","vase","vegetables","vine"],"environment":["surface","background","space"],"fauna":["bird"],"flora":["flower"],"nature":["vegetables","fruit","leaves","stem"],"objects":["fabric","shadow","plate","vase"],"people":["artist","figure"],"plants":["vine"],"unstructured":["The artist's painting depicts a still life arrangement of fruit, vegetables, and a bird, set against a textured fabric backdrop."]},"pt":{"all":["artista","fundo","ave","tecido","figura","flor","frutos","folhas","placa","sombra","espaço","caule","superfície","vaso","legumes","vinha"],"environment":["superfície","fundo","espaço"],"fauna":["ave"],"flora":["flor"],"nature":["legumes","frutos","folhas","caule"],"objects":["tecido","sombra","placa","vaso"],"people":["artista","figura"],"plants":["vinha"],"unstructured":["a pintura do artista retrata um arranjo de natureza morta de frutas, legumes e um pássaro, definido contra um pano de fundo de tecido texturizado."]}}}}