{"MU17040":{"gemma3":{"en":{"all":["animal","area","background","blood","body","creature","dog","figure","light","man","shapes","sky","space","spots","void"],"animals":["creature","dog"],"environment":["area","background","space"],"fauna":["animal"],"nature":["light","void","sky"],"objects":["blood","spots","shapes"],"people":["body","figure","man"],"unstructured":["A dark, silhouetted dog stands before a lifeless man, consumed by a chaotic burst of blood in a desolate, luminous space."]},"pt":{"all":["animal","área","fundo","sangue","corpo","criatura","cão","figura","luz","homem","formas","céu","espaço","manchas","vazio"],"animals":["criatura","cão"],"environment":["área","fundo","espaço"],"fauna":["animal"],"nature":["luz","vazio","céu"],"objects":["sangue","manchas","formas"],"people":["corpo","figura","homem"],"unstructured":["um cão escuro e silhueta está diante de um homem sem vida, consumido por uma explosão caótica de sangue em um espaço desolado e luminoso."]}}}}