{"MU17472":{"gemma3":{"en":{"all":["arms","background","bird","drawing","eyes","face","feet","figure","flowers","grid","hair","hands","legs","paper","pencil","scarf","shadows","shoes","skin","woman"],"environment":["background","paper","grid"],"fauna":["bird"],"flora":["flowers"],"nature":["hair","skin","shadows"],"objects":["pencil","scarf","shoes","drawing"],"people":["hands","feet","figure","woman","face","legs","arms","eyes"],"unstructured":["A woman sits on a grid paper, wearing a red scarf and blue pants, with a pencil drawing of a bird."]},"pt":{"all":["braços","fundo","ave","desenho","olhos","face","pés","figura","flores","grade","cabelo","mãos","pernas","papel","lápis","cachecol","sombras","sapatos","pele","mulher"],"environment":["fundo","papel","grade"],"fauna":["ave"],"flora":["flores"],"nature":["cabelo","pele","sombras"],"objects":["lápis","cachecol","sapatos","desenho"],"people":["mãos","pés","figura","mulher","face","pernas","braços","olhos"],"unstructured":["uma mulher senta-se em um papel de grade, vestindo um lenço vermelho e calças azuis, com um desenho a lápis de um pássaro."]}}}}