{"MU18288":{"gemma3":{"en":{"all":["background","branches","child","creature","deer","figure","foliage","form","hooves","landscape","leaves","legs","man","roots","staff","stick","stone","tree","vines"],"animals":["hooves","deer","legs"],"environment":["background","landscape"],"fauna":["creature"],"flora":["vines"],"nature":["roots","tree","branches","stone"],"objects":["stick","staff","form"],"people":["figure","man","child"],"plants":["leaves","foliage"],"unstructured":["A sculpted figure embraces a child amidst a stylized landscape, with a staff and intricate foliage forming a powerful, natural scene."]},"pt":{"all":["fundo","ramos","criança","criatura","veado","figura","folhagem","formulário","cascos","paisagem","folhas","pernas","homem","raízes","e-mail","stick","pedra","árvore","vinhas"],"animals":["cascos","veado","pernas"],"environment":["fundo","paisagem"],"fauna":["criatura"],"flora":["vinhas"],"nature":["raízes","árvore","ramos","pedra"],"objects":["stick","e-mail","formulário"],"people":["figura","homem","criança"],"plants":["folhas","folhagem"],"unstructured":["uma figura esculpida abraça uma criança em meio a uma paisagem estilizada, com uma equipe e folhagem intrincada formando uma cena poderosa e natural."]}}}}