{"MU18619":{"gemma3":{"en":{"all":["bird","child","collar","drawing","fabric","face","figure","hat","head","lace","paper","pattern","ribbon","shade","sketch","texture"],"animals":["bird"],"environment":["paper","drawing","sketch"],"nature":["shade","texture","pattern"],"objects":["ribbon","collar","hat","pattern"],"people":["head","figure","child","face"],"plants":["lace","fabric"],"unstructured":["A child is depicted in a detailed sketch with a patterned hat and lace collar, set against a textured paper background."]},"pt":{"all":["ave","criança","gola","desenho","tecido","face","figura","chapéu","cabeça","rendas","papel","padrão","fita","sombra","sketch","textura"],"animals":["ave"],"environment":["papel","desenho","sketch"],"nature":["sombra","textura","padrão"],"objects":["fita","gola","chapéu","padrão"],"people":["cabeça","figura","criança","face"],"plants":["rendas","tecido"],"unstructured":["uma criança é representada em um esboço detalhado com um chapéu estampado e colar de renda, definido contra um fundo de papel texturizado."]}}}}