{"MU19041":{"gemma3":{"en":{"all":["drawing","dress","figure","foot","form","hand","head","light","paper","shadow","shoe","sketch","woman"],"animals":["foot"],"environment":["paper","drawing","sketch"],"nature":["shadow","light","form"],"objects":["shoe","paper"],"people":["head","figure","woman","hand"],"plants":["dress"],"unstructured":["A woman sits in a relaxed pose on paper, rendered in charcoal, capturing a moment of quiet contemplation in a natural setting."]},"pt":{"all":["desenho","vestido","figura","pé","formulário","mão","cabeça","luz","papel","sombra","sapato","sketch","mulher"],"animals":["pé"],"environment":["papel","desenho","sketch"],"nature":["sombra","luz","formulário"],"objects":["sapato","papel"],"people":["cabeça","figura","mulher","mão"],"plants":["vestido"],"unstructured":["uma mulher senta-se em uma pose relaxada no papel, renderizada em carvão, capturando um momento de contemplação silenciosa em um ambiente natural."]}}}}