{"MU19096":{"gemma3":{"en":{"all":["Bear","Bird","Box","Child","Clock","Figure","Floor","Flowers","Ivy","Light","Man","Room","Shadow","Space","Statue","Table","Wall","Woman"],"animals":["Bear"],"environment":["Room","Floor","Space","Wall"],"fauna":["Bird"],"flora":["Ivy"],"nature":["Shadow","Light"],"objects":["Table","Box","Statue","Clock"],"people":["Woman","Figure","Child","Man"],"plants":["Flowers"],"unstructured":["A solitary man observes a child and a bear within a dimly lit room, surrounded by a clock, statue and flowers."]},"pt":{"all":["urso","pássaro","caixa","criança","relógio","figura","piso","flores","ivy","luz","homem","quarto","sombra","espaço","estátua","quadro","parede","mulher"],"animals":["urso"],"environment":["quarto","piso","espaço","parede"],"fauna":["pássaro"],"flora":["ivy"],"nature":["sombra","luz"],"objects":["quadro","caixa","estátua","relógio"],"people":["mulher","figura","criança","homem"],"plants":["flores"],"unstructured":["um homem solitário observa uma criança e um urso dentro de uma sala mal iluminada, cercada por um relógio, estátua e flores."]}}}}