{"MU20427":{"gemma3":{"en":{"all":["artist","background","canvas","color","curve","design","form","lines","shape","surface","triangle","viewer"],"environment":["canvas","surface","background"],"nature":["shape","form","design"],"objects":["triangle","curve","color","lines"],"people":["viewer","artist"],"unstructured":["The artwork presents a geometric design of triangles and curves on a vibrant yellow and green background, evoking a sense of balance and visual harmony."]},"pt":{"all":["artista","fundo","canvas","cor","curva","design","formulário","linhas","forma","superfície","triângulo","espetador"],"environment":["canvas","superfície","fundo"],"nature":["forma","formulário","design"],"objects":["triângulo","curva","cor","linhas"],"people":["espetador","artista"],"unstructured":["a obra apresenta um design geométrico de triângulos e curvas em um fundo amarelo e verde vibrante, evocando uma sensação de equilíbrio e harmonia visual."]}}}}