{"MU20181":{"gemma3":{"en":{"all":["background","branch","bush","cat","child","figure","kitten","leaf","line","mouse","paper","sky","stroke","tree"],"animals":["cat","kitten"],"environment":["paper","background"],"fauna":["mouse"],"flora":["leaf"],"nature":["sky","branch"],"objects":["stroke","line"],"people":["cat","figure","child"],"plants":["tree","bush"],"unstructured":["A child and a cat observe a playful mouse amongst a tree branch in a serene, natural environment."]},"pt":{"all":["fundo","ramo","mato","gato","criança","figura","gatinho","folha","linha","rato","papel","céu","acidente vascular cerebral","árvore"],"animals":["gato","gatinho"],"environment":["papel","fundo"],"fauna":["rato"],"flora":["folha"],"nature":["céu","ramo"],"objects":["acidente vascular cerebral","linha"],"people":["gato","figura","criança"],"plants":["árvore","mato"],"unstructured":["uma criança e um gato observam um rato brincalhão entre um galho de árvore em um ambiente sereno e natural."]}}}}