{"MU20315":{"gemma3":{"en":{"all":["artwork","background","canvas","color","composition","design","forms","gradient","lines","pattern","shapes","surface"],"environment":["canvas","surface","background"],"nature":["gradient","pattern","color"],"objects":["composition","artwork","design"],"people":["forms","shapes","lines"],"unstructured":["The artwork presents a bold, geometric design with layered colors, creating a dynamic and visually engaging composition for the viewer."]},"pt":{"all":["arte","fundo","canvas","cor","composição","design","formulários","gradiente","linhas","padrão","formas","superfície"],"environment":["canvas","superfície","fundo"],"nature":["gradiente","padrão","cor"],"objects":["composição","arte","design"],"people":["formulários","formas","linhas"],"unstructured":["a obra apresenta um design arrojado e geométrico com cores em camadas, criando uma composição dinâmica e visualmente envolvente para o espectador."]}}}}