{"MU20808":{"gemma3":{"en":{"all":["Architect","Bird","Building","Column","Door","Figure","Ground","Leaf","Light","Shadow","Sky","Space","Stone","Tree","Wall","Window"],"environment":["Building","Shadow","Wall","Ground","Space"],"fauna":["Bird"],"flora":["Leaf"],"nature":["Light","Sky","Tree"],"objects":["Stone","Window","Column","Door"],"people":["Figure","Architect"],"unstructured":["A solitary figure stands before a modern building with a large, dark roof, surrounded by a tree, stone, and a blue sky."]},"pt":{"all":["arquitecto","pássaro","edifício","coluna","porta","figura","terreno","folha","luz","sombra","céu","espaço","pedra","árvore","parede","janela"],"environment":["edifício","sombra","parede","terreno","espaço"],"fauna":["pássaro"],"flora":["folha"],"nature":["luz","céu","árvore"],"objects":["pedra","janela","coluna","porta"],"people":["figura","arquitecto"],"unstructured":["uma figura solitária está diante de um edifício moderno com um telhado grande e escuro, cercado por uma árvore, pedra e um céu azul."]}}}}